django_auxiliaries/__init__.py
django_auxiliaries/app_settings.py
django_auxiliaries/apps.py
django_auxiliaries/configuration.py
django_auxiliaries/form_fields.py
django_auxiliaries/model_fields.py
django_auxiliaries/more_tags.py
django_auxiliaries/pages.py
django_auxiliaries/requests.py
django_auxiliaries/sandbox.py
django_auxiliaries/servable.py
django_auxiliaries/tags.py
django_auxiliaries/url_signature.py
django_auxiliaries/validators.py
django_auxiliaries/variable_scope.py
django_auxiliaries/templatetags/__init__.py
django_auxiliaries/templatetags/django_auxiliaries_tags.py
django_auxiliaries-4.1.0.dist-info/AUTHORS.txt
django_auxiliaries-4.1.0.dist-info/LICENSE.txt
django_auxiliaries-4.1.0.dist-info/METADATA
django_auxiliaries-4.1.0.dist-info/WHEEL
django_auxiliaries-4.1.0.dist-info/top_level.txt
django_auxiliaries-4.1.0.dist-info/RECORD
