Metadata-Version: 2.1
Name: django-auxiliaries
Version: 4.1.0
Summary: Helpful code for managing Django app dependencies and other useful utilities when developing with Django.
Home-page: https://github.com/high-dimensional/django-auxiliaries
Author: High Dimensional Neurology Group, UCL
Author-email: pypi@highdimensional.net
License: BSD-3-Clause
Platform: any
Classifier: Framework :: Django
Classifier: Framework :: Wagtail
Classifier: Programming Language :: Python :: 3
Classifier: Programming Language :: Python :: 3.8
Classifier: License :: OSI Approved :: BSD License
Classifier: Operating System :: OS Independent
Requires-Python: ~=3.8
License-File: LICENSE.txt
License-File: AUTHORS.txt
Requires-Dist: Django (<4.2,>=4.1)
